biceps_interfaces/__init__.py
biceps_interfaces/interfaces.py
biceps_interfaces-0.3.0.dist-info/METADATA
biceps_interfaces-0.3.0.dist-info/WHEEL
biceps_interfaces-0.3.0.dist-info/top_level.txt
biceps_interfaces-0.3.0.dist-info/RECORD
